androide/__init__.py
androide/android_enhanced.py
androide/android_sdk_helper.py
androide/main.py
androide/output_helper.py
androide/platform_helper.py
androide/version.txt
android_sdk_enhanced-1.3.5.dist-info/METADATA
android_sdk_enhanced-1.3.5.dist-info/WHEEL
android_sdk_enhanced-1.3.5.dist-info/entry_points.txt
android_sdk_enhanced-1.3.5.dist-info/top_level.txt
android_sdk_enhanced-1.3.5.dist-info/zip-safe
android_sdk_enhanced-1.3.5.dist-info/RECORD
